psnprofiles_scraper/__init__.py
psnprofiles_scraper/src/BeautifulSoupFactory.py
psnprofiles_scraper/src/InvalidProfileError.py
psnprofiles_scraper/src/ProgressBar.py
psnprofiles_scraper/src/PsnProfilesScraper.py
psnprofiles_scraper/src/Utils.py
psnprofiles_scraper/src/__init__.py
psnprofiles_scraper/src/PsnProfiles/Game.py
psnprofiles_scraper/src/PsnProfiles/Level.py
psnprofiles_scraper/src/PsnProfiles/Milestone.py
psnprofiles_scraper/src/PsnProfiles/Profile.py
psnprofiles_scraper/src/PsnProfiles/ProfileSummary.py
psnprofiles_scraper/src/PsnProfiles/PsnProfilesObjectInterface.py
psnprofiles_scraper/src/PsnProfiles/Trophy.py
psnprofiles_scraper/src/PsnProfiles/__init__.py
psnprofiles_scraper-1.3.2.dist-info/LICENSE
psnprofiles_scraper-1.3.2.dist-info/WHEEL
psnprofiles_scraper-1.3.2.dist-info/METADATA
psnprofiles_scraper-1.3.2.dist-info/RECORD
