Metadata-Version: 2.1
Name: psnprofiles_scraper
Version: 1.3.2
Summary: Scrape PSNProfiles profile pages using a Python CLI script
Home-page: https://github.com/robiningelbrecht/psnprofiles-scraper
Author: Robin Ingelbrecht
Author-email: ingebrechtrobin@gmail.com
Requires-Python: >=3.9
Classifier: License :: OSI Approved :: MIT License
Classifier: Environment :: Console
Classifier: Intended Audience :: Developers
Classifier: Programming Language :: Python :: 3.9
Requires-Dist: beautifulsoup4 ~= 4.9.3
Requires-Dist: progress ~= 1.5
Requires-Dist: requests ~= 2.25
Requires-Dist: pytest >=6.2.4 ; extra == "test"
Provides-Extra: test
